swgo/__init__.py
swgo/_version.py
swgo/psa/__init__.py
swgo/psa/utils.py
swgo/psa/tests/test_adaptive_centroid.py
swgo/psa/tests/test_adaptive_sum.py
swgo/psa/tests/test_differentiate.py
swgo/psa/tests/test_psa_import.py
swgo/psa/tests/test_upsample.py
swgo/tests/test_import.py
swgo_psa-0.3.1.dist-info/LICENSE
swgo_psa-0.3.1.dist-info/METADATA
swgo_psa-0.3.1.dist-info/WHEEL
swgo_psa-0.3.1.dist-info/top_level.txt
swgo_psa-0.3.1.dist-info/RECORD
